fivccliche/__init__.py
fivccliche/cli.py
fivccliche/modules/__init__.py
fivccliche/modules/agent_chats/__init__.py
fivccliche/modules/agent_chats/methods.py
fivccliche/modules/agent_chats/models.py
fivccliche/modules/agent_chats/routers.py
fivccliche/modules/agent_chats/schemas.py
fivccliche/modules/agent_chats/services.py
fivccliche/modules/agent_configs/__init__.py
fivccliche/modules/agent_configs/methods.py
fivccliche/modules/agent_configs/models.py
fivccliche/modules/agent_configs/routers.py
fivccliche/modules/agent_configs/schemas.py
fivccliche/modules/agent_configs/services.py
fivccliche/modules/users/__init__.py
fivccliche/modules/users/methods.py
fivccliche/modules/users/models.py
fivccliche/modules/users/routers.py
fivccliche/modules/users/schemas.py
fivccliche/modules/users/services.py
fivccliche/modules/users/sso.py
fivccliche/services/__init__.py
fivccliche/services/implements/__init__.py
fivccliche/services/implements/db.py
fivccliche/services/implements/modules.py
fivccliche/services/interfaces/__init__.py
fivccliche/services/interfaces/agent_chats.py
fivccliche/services/interfaces/agent_configs.py
fivccliche/services/interfaces/auth.py
fivccliche/services/interfaces/db.py
fivccliche/services/interfaces/modules.py
fivccliche/settings/__init__.py
fivccliche/settings/services.yml
fivccliche/utils/__init__.py
fivccliche/utils/deps.py
fivccliche/utils/exceptions.py
fivccliche/utils/middleware.py
fivccliche/utils/permissions.py
fivccliche/utils/schemas.py
fivccliche-0.1.18.dist-info/licenses/LICENSE
fivccliche-0.1.18.dist-info/METADATA
fivccliche-0.1.18.dist-info/WHEEL
fivccliche-0.1.18.dist-info/entry_points.txt
fivccliche-0.1.18.dist-info/top_level.txt
fivccliche-0.1.18.dist-info/RECORD
