Metadata-Version: 2.4
Name: fivccliche
Version: 0.1.18
Summary: A modern async Python framework for building scalable applications with FastAPI and SQLModel
Author-email: Charlie Zhang <sunnypig2002@gmail.com>
Project-URL: Homepage, https://github.com/MindFiv/FivcCliche
Project-URL: Repository, https://github.com/MindFiv/FivcCliche.git
Project-URL: Issues, https://github.com/MindFiv/FivcCliche/issues
Keywords: fastapi,sqlmodel,async,orm,rest-api
Requires-Python: >=3.10
License-File: LICENSE
Requires-Dist: fastapi>=0.104.0
Requires-Dist: sqlmodel>=0.0.14
Requires-Dist: uvicorn[standard]>=0.24.0
Requires-Dist: pydantic>=2.0.0
Requires-Dist: pydantic-settings>=2.0.0
Requires-Dist: pydantic[email]>=2.0.0
Requires-Dist: python-multipart>=0.0.6
Requires-Dist: python-dotenv>=1.0.0
Requires-Dist: typer>=0.9.0
Requires-Dist: rich>=13.0.0
Requires-Dist: fivcplayground>=0.1.18
Requires-Dist: fivcplayground[strands]>=0.1.18
Requires-Dist: fivcplayground[chroma]>=0.1.18
Requires-Dist: fivcglue>=0.1.5
Requires-Dist: passlib[argon2]>=1.7.4
Requires-Dist: pyjwt>=2.10.1
Requires-Dist: greenlet>=3.2.4
Requires-Dist: python-cas>=1.7.1
Requires-Dist: fastapi-cdn-host>=0.9.3
Requires-Dist: pydantic-strict-partial>=0.6.2
Provides-Extra: dev
Requires-Dist: pytest>=7.4.0; extra == "dev"
Requires-Dist: pytest-asyncio>=0.21.0; extra == "dev"
Requires-Dist: httpx>=0.25.0; extra == "dev"
Requires-Dist: black>=23.0.0; extra == "dev"
Requires-Dist: ruff>=0.1.0; extra == "dev"
Requires-Dist: mypy>=1.5.0; extra == "dev"
Requires-Dist: pytest-cov>=4.1.0; extra == "dev"
Requires-Dist: aiosqlite>=0.21.0; extra == "dev"
Dynamic: license-file
